README.rst
setup.cfg
setup.py
src/django_bootstrap_carousel/__init__.py
src/django_bootstrap_carousel/admin.py
src/django_bootstrap_carousel/models.py
src/django_bootstrap_carousel.egg-info/PKG-INFO
src/django_bootstrap_carousel.egg-info/SOURCES.txt
src/django_bootstrap_carousel.egg-info/dependency_links.txt
src/django_bootstrap_carousel.egg-info/not-zip-safe
src/django_bootstrap_carousel.egg-info/requires.txt
src/django_bootstrap_carousel.egg-info/top_level.txt
src/django_bootstrap_carousel/migrations/0001_initial.py
src/django_bootstrap_carousel/migrations/0002_carouselitem_url.py
src/django_bootstrap_carousel/migrations/__init__.py
src/django_bootstrap_carousel/south_migrations/0001_initial.py
src/django_bootstrap_carousel/south_migrations/0002_auto__add_field_carouselitem_url.py
src/django_bootstrap_carousel/south_migrations/__init__.py
src/django_bootstrap_carousel/templatetags/__init__.py
src/django_bootstrap_carousel/templatetags/bootstrap_carousel_tags.py