Metadata-Version: 1.1
Name: django-bootstrap-carousel
Version: 0.2
Summary: Django Bootstrap Carousel Component
Home-page: https://github.com/cdchen/django-bootstrap-carousel
Author: cdchen
Author-email: cdchen@nicestudio.com.tw
License: MIT License
Download-URL: https://github.com/cdchen/django-bootstrap-carousel/tarball/master
Platform: UNKNOWN
Classifier: Development Status :: 4 - Beta
Classifier: Development Status :: 5 - Production/Stable
Classifier: Environment :: Web Environment
Classifier: Framework :: Django
Classifier: Intended Audience :: Developers
Classifier: License :: OSI Approved :: MIT License
Classifier: Operating System :: OS Independent
Classifier: Programming Language :: Python
Classifier: Topic :: Utilities
